scrapy_kit/__init__.py
scrapy_kit/middlewares/__init__.py
scrapy_kit/middlewares/proxy_connection_close.py
scrapy_kit/pipelines/__init__.py
scrapy_kit/pipelines/crawl_one_pipeline.py
scrapy_kit/pipelines/mongo_pipeline.py
scrapy_kit/playwright/__init__.py
scrapy_kit/playwright/request.py
scrapy_kit-0.1.12.dist-info/LICENSE
scrapy_kit-0.1.12.dist-info/METADATA
scrapy_kit-0.1.12.dist-info/WHEEL
scrapy_kit-0.1.12.dist-info/RECORD
